applitools/common/__init__.py
applitools/common/__version__.py
applitools/common/_dynamic_regions.py
applitools/common/_dynamic_text_type.py
applitools/common/batch_close.py
applitools/common/command_context.py
applitools/common/command_executor.py
applitools/common/config.py
applitools/common/connection.py
applitools/common/context_vars.py
applitools/common/cut.py
applitools/common/deprecated.py
applitools/common/ec_client_settings.py
applitools/common/errors.py
applitools/common/extract_text.py
applitools/common/eyes.py
applitools/common/feature.py
applitools/common/geometry.py
applitools/common/layout_breakpoints_options.py
applitools/common/locators.py
applitools/common/logger.py
applitools/common/marshaller.py
applitools/common/match.py
applitools/common/mmallow.py
applitools/common/mmallow_version.py
applitools/common/object_registry.py
applitools/common/optional_deps.py
applitools/common/protocol.py
applitools/common/py.typed
applitools/common/runner.py
applitools/common/schema.py
applitools/common/schema_fields.py
applitools/common/server.py
applitools/common/target.py
applitools/common/test_results.py
applitools/common/triggers.py
applitools/common/validators.py
applitools/common/accessibility/__init__.py
applitools/common/accessibility/_guidelines_version.py
applitools/common/accessibility/_level.py
applitools/common/accessibility/_region_type.py
applitools/common/accessibility/_status.py
applitools/common/fluent/__init__.py
applitools/common/fluent/check_settings.py
applitools/common/fluent/images_check_settings.py
applitools/common/fluent/region.py
applitools/common/fluent/target.py
applitools/common/fluent/target_path.py
applitools/common/fluent/web_check_settings.py
applitools/common/fluent/web_target.py
applitools/common/selenium/__init__.py
applitools/common/selenium/config.py
applitools/common/selenium/misc.py
applitools/common/ultrafastgrid/__init__.py
applitools/common/ultrafastgrid/_android_multi_device_target.py
eyes_common-6.5.18.dist-info/licenses/LICENSE
eyes_common-6.5.18.dist-info/METADATA
eyes_common-6.5.18.dist-info/WHEEL
eyes_common-6.5.18.dist-info/top_level.txt
eyes_common-6.5.18.dist-info/RECORD
