Metadata-Version: 2.4
Name: eyes-common
Version: 6.5.18
Summary: Applitools Python SDK. Common code package
Author-email: Applitools Team <team@applitools.com>
License-Expression: LicenseRef-Proprietary
Project-URL: Homepage, https://applitools.com
Keywords: applitools,eyes,eyes_images,eyes_selenium,eyes_playwright
Classifier: Programming Language :: Python
Classifier: Development Status :: 5 - Production/Stable
Classifier: Intended Audience :: Developers
Classifier: Operating System :: MacOS
Classifier: Operating System :: Microsoft :: Windows
Classifier: Operating System :: POSIX :: Linux
Classifier: Topic :: Software Development :: Quality Assurance
Classifier: Topic :: Software Development :: Testing
Requires-Python: <4,>=3.7
License-File: LICENSE
Requires-Dist: attrs<26,>=23
Requires-Dist: core-universal4==4.54.3
Requires-Dist: marshmallow<4,>=3.15
Requires-Dist: websocket-client<2,>=1.2; python_version >= "3.4"
Dynamic: license-file
